{
    "folder": "nodes_150",
    "num_nodes": 150,
    "num_files": 10,
    "num_runs": 5,
    "algorithms": [
        "Greedy",
        "PSO",
        "GA",
        "PSO-Adaptive",
        "PSO-L\u00e9vy"
    ],
    "results": {
        "nodes_150_1": {
            "Greedy": {
                "values": [
                    5588.608374821477,
                    5588.608374821477,
                    5588.608374821477,
                    5588.608374821477,
                    5588.608374821477
                ],
                "mean": 5588.608374821477,
                "median": 5588.608374821477,
                "std": 0.0,
                "min": 5588.608374821477,
                "max": 5588.608374821477,
                "cv": 0.0
            },
            "PSO": {
                "values": [
                    7241.849955720527,
                    7171.055808578658,
                    7100.709014737706,
                    7198.6236423727905,
                    7178.171011119793
                ],
                "mean": 7178.0818865058945,
                "median": 7178.171011119793,
                "std": 45.87867780429224,
                "min": 7100.709014737706,
                "max": 7241.849955720527,
                "cv": 0.006391495462114991
            },
            "GA": {
                "values": [
                    4055.426751128392,
                    4124.722520868929,
                    4264.453975530823,
                    4441.841751397308,
                    4174.422035317455
                ],
                "mean": 4212.173406848582,
                "median": 4174.422035317455,
                "std": 133.50890902113028,
                "min": 4055.426751128392,
                "max": 4441.841751397308,
                "cv": 0.031695966933378825
            },
            "PSO-Adaptive": {
                "values": [
                    7235.797632067162,
                    6978.775175616774,
                    7226.888417505633,
                    7173.404200069475,
                    7144.917025412997
                ],
                "mean": 7151.956490134408,
                "median": 7173.404200069475,
                "std": 92.89290268178011,
                "min": 6978.775175616774,
                "max": 7235.797632067162,
                "cv": 0.012988460263973775
            },
            "PSO-L\u00e9vy": {
                "values": [
                    7123.363059151057,
                    7186.243597787353,
                    7196.138472291871,
                    7148.92572315649,
                    7185.477790816026
                ],
                "mean": 7168.029728640559,
                "median": 7185.477790816026,
                "std": 27.51856014202193,
                "min": 7123.363059151057,
                "max": 7196.138472291871,
                "cv": 0.0038390689190460313
            }
        },
        "nodes_150_2": {
            "Greedy": {
                "values": [
                    5660.862269996572,
                    5660.862269996572,
                    5660.862269996572,
                    5660.862269996572,
                    5660.862269996572
                ],
                "mean": 5660.862269996572,
                "median": 5660.862269996572,
                "std": 0.0,
                "min": 5660.862269996572,
                "max": 5660.862269996572,
                "cv": 0.0
            },
            "PSO": {
                "values": [
                    7199.724939028371,
                    7416.164123198655,
                    7352.701282712549,
                    7566.2064366567865,
                    7173.52842587581
                ],
                "mean": 7341.665041494435,
                "median": 7352.701282712549,
                "std": 144.57362424468275,
                "min": 7173.52842587581,
                "max": 7566.2064366567865,
                "cv": 0.019692211974744904
            },
            "GA": {
                "values": [
                    4348.0787392214725,
                    4504.969939327284,
                    4385.176703947008,
                    4473.275523815067,
                    4235.091036583317
                ],
                "mean": 4389.318388578829,
                "median": 4385.176703947008,
                "std": 95.84155683403011,
                "min": 4235.091036583317,
                "max": 4504.969939327284,
                "cv": 0.02183517994124405
            },
            "PSO-Adaptive": {
                "values": [
                    7461.077999508562,
                    7539.244543936266,
                    7415.156833894202,
                    7208.004131135933,
                    7513.990301632055
                ],
                "mean": 7427.494762021403,
                "median": 7461.077999508562,
                "std": 117.83521331728478,
                "min": 7208.004131135933,
                "max": 7539.244543936266,
                "cv": 0.015864731930853058
            },
            "PSO-L\u00e9vy": {
                "values": [
                    7308.781430995709,
                    7405.167043123024,
                    7368.029499022908,
                    7176.989882041193,
                    7271.248429401919
                ],
                "mean": 7306.04325691695,
                "median": 7308.781430995709,
                "std": 79.42388858291314,
                "min": 7176.989882041193,
                "max": 7405.167043123024,
                "cv": 0.01087098526383882
            }
        },
        "nodes_150_3": {
            "Greedy": {
                "values": [
                    5878.109534100779,
                    5878.109534100779,
                    5878.109534100779,
                    5878.109534100779,
                    5878.109534100779
                ],
                "mean": 5878.109534100779,
                "median": 5878.109534100779,
                "std": 0.0,
                "min": 5878.109534100779,
                "max": 5878.109534100779,
                "cv": 0.0
            },
            "PSO": {
                "values": [
                    7945.580199190748,
                    7794.389797248887,
                    7776.09193179967,
                    7888.997547865413,
                    7830.391701268961
                ],
                "mean": 7847.090235474736,
                "median": 7830.391701268961,
                "std": 62.5354813576198,
                "min": 7776.09193179967,
                "max": 7945.580199190748,
                "cv": 0.007969257327373719
            },
            "GA": {
                "values": [
                    4615.009187303585,
                    4638.358315056017,
                    4612.575344742561,
                    4885.942751908819,
                    4838.991395535163
                ],
                "mean": 4718.175398909229,
                "median": 4638.358315056017,
                "std": 119.08635127931424,
                "min": 4612.575344742561,
                "max": 4885.942751908819,
                "cv": 0.025239916113937857
            },
            "PSO-Adaptive": {
                "values": [
                    7786.697892331326,
                    7900.828405400261,
                    7908.028615513376,
                    7880.505706553556,
                    7870.92292271676
                ],
                "mean": 7869.396708503055,
                "median": 7880.505706553556,
                "std": 43.46310889204644,
                "min": 7786.697892331326,
                "max": 7908.028615513376,
                "cv": 0.005523054752733917
            },
            "PSO-L\u00e9vy": {
                "values": [
                    7888.055915178892,
                    7935.915919835981,
                    7884.751591093845,
                    7858.772117458227,
                    8055.700404263388
                ],
                "mean": 7924.639189566066,
                "median": 7888.055915178892,
                "std": 70.10283062522609,
                "min": 7858.772117458227,
                "max": 8055.700404263388,
                "cv": 0.008846185794493535
            }
        },
        "nodes_150_4": {
            "Greedy": {
                "values": [
                    5852.781003338642,
                    5852.781003338642,
                    5852.781003338642,
                    5852.781003338642,
                    5852.781003338642
                ],
                "mean": 5852.781003338642,
                "median": 5852.781003338642,
                "std": 0.0,
                "min": 5852.781003338642,
                "max": 5852.781003338642,
                "cv": 0.0
            },
            "PSO": {
                "values": [
                    7244.222628213967,
                    7296.6648952467995,
                    7141.448705305042,
                    7197.283552317066,
                    7188.9046094965515
                ],
                "mean": 7213.704878115886,
                "median": 7197.283552317066,
                "std": 52.762420883168616,
                "min": 7141.448705305042,
                "max": 7296.6648952467995,
                "cv": 0.007314191774497627
            },
            "GA": {
                "values": [
                    4327.458065760685,
                    4136.758383284128,
                    4348.834171330467,
                    4309.033988427155,
                    4229.3475988232885
                ],
                "mean": 4270.286441525144,
                "median": 4309.033988427155,
                "std": 78.03261375297745,
                "min": 4136.758383284128,
                "max": 4348.834171330467,
                "cv": 0.0182733909824344
            },
            "PSO-Adaptive": {
                "values": [
                    6953.625977162054,
                    7097.664552855144,
                    7002.572050228695,
                    7320.857254352061,
                    6886.1504005570605
                ],
                "mean": 7052.174047031003,
                "median": 7002.572050228695,
                "std": 150.99402860155965,
                "min": 6886.1504005570605,
                "max": 7320.857254352061,
                "cv": 0.021410990085409025
            },
            "PSO-L\u00e9vy": {
                "values": [
                    7054.286267395287,
                    7271.916914118307,
                    7137.298164284351,
                    7040.489968046886,
                    7134.456075984128
                ],
                "mean": 7127.689477965791,
                "median": 7134.456075984128,
                "std": 82.3789449954215,
                "min": 7040.489968046886,
                "max": 7271.916914118307,
                "cv": 0.011557594540290223
            }
        },
        "nodes_150_5": {
            "Greedy": {
                "values": [
                    6076.042352752642,
                    6076.042352752642,
                    6076.042352752642,
                    6076.042352752642,
                    6076.042352752642
                ],
                "mean": 6076.042352752642,
                "median": 6076.042352752642,
                "std": 0.0,
                "min": 6076.042352752642,
                "max": 6076.042352752642,
                "cv": 0.0
            },
            "PSO": {
                "values": [
                    7184.171892186493,
                    7141.295196665355,
                    7264.906267910909,
                    7024.5219487412505,
                    7192.26542867669
                ],
                "mean": 7161.4321468361395,
                "median": 7184.171892186493,
                "std": 79.15122251035199,
                "min": 7024.5219487412505,
                "max": 7264.906267910909,
                "cv": 0.01105242930289025
            },
            "GA": {
                "values": [
                    4039.955258433656,
                    4109.345532658969,
                    4249.698788354929,
                    4445.4258279224105,
                    4372.726828842188
                ],
                "mean": 4243.43044724243,
                "median": 4249.698788354929,
                "std": 152.93128979431472,
                "min": 4039.955258433656,
                "max": 4445.4258279224105,
                "cv": 0.036039541992186126
            },
            "PSO-Adaptive": {
                "values": [
                    7155.813959558587,
                    7192.881448697875,
                    7035.067021503635,
                    6968.24706590033,
                    7224.850044459787
                ],
                "mean": 7115.3719080240435,
                "median": 7155.813959558587,
                "std": 97.69682160051829,
                "min": 6968.24706590033,
                "max": 7224.850044459787,
                "cv": 0.013730388637921379
            },
            "PSO-L\u00e9vy": {
                "values": [
                    6944.34457448826,
                    7248.118672437935,
                    6898.495146896978,
                    7284.3034920989385,
                    7118.084883390422
                ],
                "mean": 7098.669353862507,
                "median": 7118.084883390422,
                "std": 155.60073621386235,
                "min": 6898.495146896978,
                "max": 7284.3034920989385,
                "cv": 0.021919704730182614
            }
        },
        "nodes_150_6": {
            "Greedy": {
                "values": [
                    5746.000084124986,
                    5746.000084124986,
                    5746.000084124986,
                    5746.000084124986,
                    5746.000084124986
                ],
                "mean": 5746.000084124986,
                "median": 5746.000084124986,
                "std": 0.0,
                "min": 5746.000084124986,
                "max": 5746.000084124986,
                "cv": 0.0
            },
            "PSO": {
                "values": [
                    7455.250273235366,
                    7338.463858263084,
                    7251.015575015507,
                    7357.66225491572,
                    7210.192848919909
                ],
                "mean": 7322.516962069916,
                "median": 7338.463858263084,
                "std": 85.83330559403747,
                "min": 7210.192848919909,
                "max": 7455.250273235366,
                "cv": 0.011721830900310303
            },
            "GA": {
                "values": [
                    4179.9024499058005,
                    4478.663948376023,
                    4282.156485008524,
                    4182.079844722769,
                    4423.431208339513
                ],
                "mean": 4309.246787270526,
                "median": 4282.156485008524,
                "std": 122.78072312363757,
                "min": 4179.9024499058005,
                "max": 4478.663948376023,
                "cv": 0.02849238606763731
            },
            "PSO-Adaptive": {
                "values": [
                    7158.683760413481,
                    7301.522393775158,
                    7566.394790740489,
                    7205.265275329701,
                    6905.871387733785
                ],
                "mean": 7227.547521598523,
                "median": 7205.265275329701,
                "std": 214.01121686491913,
                "min": 6905.871387733785,
                "max": 7566.394790740489,
                "cv": 0.029610489066363977
            },
            "PSO-L\u00e9vy": {
                "values": [
                    7324.2474838540265,
                    7298.495254182929,
                    7244.395263810537,
                    7405.790349588416,
                    7314.379032719742
                ],
                "mean": 7317.461476831129,
                "median": 7314.379032719742,
                "std": 52.06905069674166,
                "min": 7244.395263810537,
                "max": 7405.790349588416,
                "cv": 0.007115725974315683
            }
        },
        "nodes_150_7": {
            "Greedy": {
                "values": [
                    5753.909536272984,
                    5753.909536272984,
                    5753.909536272984,
                    5753.909536272984,
                    5753.909536272984
                ],
                "mean": 5753.909536272984,
                "median": 5753.909536272984,
                "std": 0.0,
                "min": 5753.909536272984,
                "max": 5753.909536272984,
                "cv": 0.0
            },
            "PSO": {
                "values": [
                    7239.757830383493,
                    7153.580818965938,
                    7248.684827958756,
                    7410.434701478278,
                    7186.6066521000275
                ],
                "mean": 7247.812966177298,
                "median": 7239.757830383493,
                "std": 88.47302933540078,
                "min": 7153.580818965938,
                "max": 7410.434701478278,
                "cv": 0.01220685877909236
            },
            "GA": {
                "values": [
                    4259.138565130366,
                    4326.990881665247,
                    4546.813362587973,
                    4157.483515860039,
                    4586.442828560944
                ],
                "mean": 4375.373830760914,
                "median": 4326.990881665247,
                "std": 165.69210661488398,
                "min": 4157.483515860039,
                "max": 4586.442828560944,
                "cv": 0.037869245697359936
            },
            "PSO-Adaptive": {
                "values": [
                    7344.394543577082,
                    6952.474005257822,
                    7320.71098545771,
                    7246.060734480978,
                    7270.232364082698
                ],
                "mean": 7226.774526571258,
                "median": 7270.232364082698,
                "std": 141.53433799478273,
                "min": 6952.474005257822,
                "max": 7344.394543577082,
                "cv": 0.019584717563055572
            },
            "PSO-L\u00e9vy": {
                "values": [
                    7195.024727073809,
                    6932.435027439138,
                    7146.799291312649,
                    7113.923088529926,
                    7142.813812922112
                ],
                "mean": 7106.199189455527,
                "median": 7142.813812922112,
                "std": 90.70018486613432,
                "min": 6932.435027439138,
                "max": 7195.024727073809,
                "cv": 0.012763529764366727
            }
        },
        "nodes_150_8": {
            "Greedy": {
                "values": [
                    5517.247628847138,
                    5517.247628847138,
                    5517.247628847138,
                    5517.247628847138,
                    5517.247628847138
                ],
                "mean": 5517.247628847138,
                "median": 5517.247628847138,
                "std": 0.0,
                "min": 5517.247628847138,
                "max": 5517.247628847138,
                "cv": 0.0
            },
            "PSO": {
                "values": [
                    6924.832298665993,
                    6957.006546115593,
                    7013.722251837692,
                    6932.67871908091,
                    6911.921350954864
                ],
                "mean": 6948.0322333310105,
                "median": 6932.67871908091,
                "std": 35.982440205291006,
                "min": 6911.921350954864,
                "max": 7013.722251837692,
                "cv": 0.00517879580821121
            },
            "GA": {
                "values": [
                    4069.478305281805,
                    4177.651606841163,
                    4037.763930418673,
                    3891.967238330495,
                    4157.324727902456
                ],
                "mean": 4066.8371617549187,
                "median": 4069.478305281805,
                "std": 101.88185255971885,
                "min": 3891.967238330495,
                "max": 4177.651606841163,
                "cv": 0.025051864263912368
            },
            "PSO-Adaptive": {
                "values": [
                    7134.965034464828,
                    6729.649422747972,
                    7254.316629482203,
                    6864.946223570772,
                    7095.319552805149
                ],
                "mean": 7015.839372614185,
                "median": 7095.319552805149,
                "std": 190.8155414165732,
                "min": 6729.649422747972,
                "max": 7254.316629482203,
                "cv": 0.027197820714283696
            },
            "PSO-L\u00e9vy": {
                "values": [
                    6839.021908674608,
                    7136.577128516685,
                    6815.881292631596,
                    6880.432596111962,
                    6791.627160130416
                ],
                "mean": 6892.708017213054,
                "median": 6839.021908674608,
                "std": 125.39913312276877,
                "min": 6791.627160130416,
                "max": 7136.577128516685,
                "cv": 0.01819301395178955
            }
        },
        "nodes_150_9": {
            "Greedy": {
                "values": [
                    5659.879844689918,
                    5659.879844689918,
                    5659.879844689918,
                    5659.879844689918,
                    5659.879844689918
                ],
                "mean": 5659.879844689918,
                "median": 5659.879844689918,
                "std": 0.0,
                "min": 5659.879844689918,
                "max": 5659.879844689918,
                "cv": 0.0
            },
            "PSO": {
                "values": [
                    7470.617100663637,
                    7307.790847586108,
                    7446.434797516292,
                    7408.911810709377,
                    7374.725867269585
                ],
                "mean": 7401.696084749,
                "median": 7408.911810709377,
                "std": 57.1827102425569,
                "min": 7307.790847586108,
                "max": 7470.617100663637,
                "cv": 0.007725622558372854
            },
            "GA": {
                "values": [
                    4505.48456298996,
                    4564.378653778308,
                    4368.066851703952,
                    4330.879563390441,
                    4536.436528568417
                ],
                "mean": 4461.049232086216,
                "median": 4505.48456298996,
                "std": 93.72788080455305,
                "min": 4330.879563390441,
                "max": 4564.378653778308,
                "cv": 0.021010277163141973
            },
            "PSO-Adaptive": {
                "values": [
                    7439.188633970528,
                    7047.364962217931,
                    7360.235707092304,
                    7431.975668948765,
                    7270.187061979591
                ],
                "mean": 7309.790406841824,
                "median": 7360.235707092304,
                "std": 144.67439765755344,
                "min": 7047.364962217931,
                "max": 7439.188633970528,
                "cv": 0.019791866743831803
            },
            "PSO-L\u00e9vy": {
                "values": [
                    7328.392549316907,
                    7435.0799470614875,
                    7465.757612276044,
                    7288.367561429361,
                    7411.323281311876
                ],
                "mean": 7385.784190279135,
                "median": 7411.323281311876,
                "std": 66.72610443029185,
                "min": 7288.367561429361,
                "max": 7465.757612276044,
                "cv": 0.009034396715532795
            }
        },
        "nodes_150_10": {
            "Greedy": {
                "values": [
                    5700.3297453529285,
                    5700.3297453529285,
                    5700.3297453529285,
                    5700.3297453529285,
                    5700.3297453529285
                ],
                "mean": 5700.3297453529285,
                "median": 5700.3297453529285,
                "std": 0.0,
                "min": 5700.3297453529285,
                "max": 5700.3297453529285,
                "cv": 0.0
            },
            "PSO": {
                "values": [
                    6817.939411857809,
                    6734.9599212543335,
                    6649.787465840763,
                    6941.992221343021,
                    6885.155106484834
                ],
                "mean": 6805.966825356152,
                "median": 6817.939411857809,
                "std": 104.26025879288939,
                "min": 6649.787465840763,
                "max": 6941.992221343021,
                "cv": 0.015318949014629308
            },
            "GA": {
                "values": [
                    3936.8476351078243,
                    3947.90044791624,
                    4294.171551165582,
                    3885.1512298699,
                    3765.4262029535485
                ],
                "mean": 3965.899413402619,
                "median": 3936.8476351078243,
                "std": 176.4314837344665,
                "min": 3765.4262029535485,
                "max": 4294.171551165582,
                "cv": 0.04448713024294627
            },
            "PSO-Adaptive": {
                "values": [
                    6883.819498993305,
                    6861.929239395129,
                    6654.112051322173,
                    6975.934517877677,
                    6854.441666871981
                ],
                "mean": 6846.047394892053,
                "median": 6861.929239395129,
                "std": 105.31787071898017,
                "min": 6654.112051322173,
                "max": 6975.934517877677,
                "cv": 0.015383748408981152
            },
            "PSO-L\u00e9vy": {
                "values": [
                    6835.370594192402,
                    6842.286080798716,
                    6846.216448255355,
                    6755.538829489112,
                    6713.63581113995
                ],
                "mean": 6798.609552775108,
                "median": 6835.370594192402,
                "std": 54.038974334096295,
                "min": 6713.63581113995,
                "max": 6846.216448255355,
                "cv": 0.007948533286786305
            }
        }
    }
}