[
    {
        "id": 0,
        "x": 27.441,
        "y": 35.759,
        "z": 30.138,
        "energy_residual": 100.0,
        "energy_node": 100.0
    },
    {
        "id": 1,
        "x": 27.244,
        "y": 21.183,
        "z": 82.295,
        "energy_residual": 100.0,
        "energy_node": 100.0
    },
    {
        "id": 2,
        "x": 21.879,
        "y": 44.589,
        "z": 148.183,
        "energy_residual": 100.0,
        "energy_node": 100.0
    },
    {
        "id": 3,
        "x": 19.172,
        "y": 39.586,
        "z": 176.445,
        "energy_residual": 100.0,
        "energy_node": 100.0
    },
    {
        "id": 4,
        "x": 28.402,
        "y": 46.28,
        "z": 203.552,
        "energy_residual": 100.0,
        "energy_node": 100.0
    },
    {
        "id": 5,
        "x": 4.356,
        "y": 1.011,
        "z": 291.631,
        "energy_residual": 100.0,
        "energy_node": 100.0
    },
    {
        "id": 6,
        "x": 38.908,
        "y": 43.501,
        "z": 348.931,
        "energy_residual": 100.0,
        "energy_node": 100.0
    },
    {
        "id": 7,
        "x": 39.958,
        "y": 23.074,
        "z": 389.026,
        "energy_residual": 100.0,
        "energy_node": 100.0
    },
    {
        "id": 8,
        "x": 5.914,
        "y": 81.996,
        "z": 7.168,
        "energy_residual": 100.0,
        "energy_node": 100.0
    },
    {
        "id": 9,
        "x": 47.233,
        "y": 76.092,
        "z": 70.733,
        "energy_residual": 100.0,
        "energy_node": 100.0
    },
    {
        "id": 10,
        "x": 13.228,
        "y": 88.712,
        "z": 122.808,
        "energy_residual": 100.0,
        "energy_node": 100.0
    },
    {
        "id": 11,
        "x": 28.422,
        "y": 50.939,
        "z": 180.882,
        "energy_residual": 100.0,
        "energy_node": 100.0
    },
    {
        "id": 12,
        "x": 30.605,
        "y": 80.847,
        "z": 247.187,
        "energy_residual": 100.0,
        "energy_node": 100.0
    },
    {
        "id": 13,
        "x": 34.091,
        "y": 67.975,
        "z": 271.852,
        "energy_residual": 100.0,
        "energy_node": 100.0
    },
    {
        "id": 14,
        "x": 34.882,
        "y": 53.011,
        "z": 333.338,
        "energy_residual": 100.0,
        "energy_node": 100.0
    },
    {
        "id": 15,
        "x": 33.532,
        "y": 60.519,
        "z": 356.446,
        "energy_residual": 100.0,
        "energy_node": 100.0
    },
    {
        "id": 16,
        "x": 15.771,
        "y": 118.186,
        "z": 28.51,
        "energy_residual": 100.0,
        "energy_node": 100.0
    },
    {
        "id": 17,
        "x": 21.93,
        "y": 149.419,
        "z": 55.102,
        "energy_residual": 100.0,
        "energy_node": 100.0
    },
    {
        "id": 18,
        "x": 10.444,
        "y": 108.065,
        "z": 132.655,
        "energy_residual": 100.0,
        "energy_node": 100.0
    },
    {
        "id": 19,
        "x": 12.665,
        "y": 123.316,
        "z": 162.221,
        "energy_residual": 100.0,
        "energy_node": 100.0
    },
    {
        "id": 20,
        "x": 7.948,
        "y": 105.519,
        "z": 232.816,
        "energy_residual": 100.0,
        "energy_node": 100.0
    },
    {
        "id": 21,
        "x": 6.909,
        "y": 109.829,
        "z": 268.436,
        "energy_residual": 100.0,
        "energy_node": 100.0
    },
    {
        "id": 22,
        "x": 41.05,
        "y": 104.855,
        "z": 341.897,
        "energy_residual": 100.0,
        "energy_node": 100.0
    },
    {
        "id": 23,
        "x": 4.805,
        "y": 148.823,
        "z": 373.433,
        "energy_residual": 100.0,
        "energy_node": 100.0
    },
    {
        "id": 24,
        "x": 48.838,
        "y": 180.242,
        "z": 36.963,
        "energy_residual": 100.0,
        "energy_node": 100.0
    },
    {
        "id": 25,
        "x": 1.959,
        "y": 164.14,
        "z": 56.01,
        "energy_residual": 100.0,
        "energy_node": 100.0
    },
    {
        "id": 26,
        "x": 14.807,
        "y": 155.936,
        "z": 115.899,
        "energy_residual": 100.0,
        "energy_node": 100.0
    },
    {
        "id": 27,
        "x": 20.713,
        "y": 153.207,
        "z": 184.624,
        "energy_residual": 100.0,
        "energy_node": 100.0
    },
    {
        "id": 28,
        "x": 28.33,
        "y": 163.269,
        "z": 226.162,
        "energy_residual": 100.0,
        "energy_node": 100.0
    },
    {
        "id": 29,
        "x": 4.697,
        "y": 178.797,
        "z": 296.465,
        "energy_residual": 100.0,
        "energy_node": 100.0
    },
    {
        "id": 30,
        "x": 15.928,
        "y": 183.371,
        "z": 306.59,
        "energy_residual": 100.0,
        "energy_node": 100.0
    },
    {
        "id": 31,
        "x": 35.816,
        "y": 164.47,
        "z": 359.16,
        "energy_residual": 100.0,
        "energy_node": 100.0
    },
    {
        "id": 32,
        "x": 29.326,
        "y": 201.005,
        "z": 41.447,
        "energy_residual": 100.0,
        "energy_node": 100.0
    },
    {
        "id": 33,
        "x": 0.235,
        "y": 233.891,
        "z": 63.5,
        "energy_residual": 100.0,
        "energy_node": 100.0
    },
    {
        "id": 34,
        "x": 36.76,
        "y": 248.109,
        "z": 112.438,
        "energy_residual": 100.0,
        "energy_node": 100.0
    },
    {
        "id": 35,
        "x": 28.808,
        "y": 229.602,
        "z": 178.613,
        "energy_residual": 100.0,
        "energy_node": 100.0
    },
    {
        "id": 36,
        "x": 11.154,
        "y": 247.637,
        "z": 222.356,
        "energy_residual": 100.0,
        "energy_node": 100.0
    },
    {
        "id": 37,
        "x": 42.32,
        "y": 234.974,
        "z": 264.872,
        "energy_residual": 100.0,
        "energy_node": 100.0
    },
    {
        "id": 38,
        "x": 40.69,
        "y": 219.825,
        "z": 344.055,
        "energy_residual": 100.0,
        "energy_node": 100.0
    },
    {
        "id": 39,
        "x": 29.064,
        "y": 244.087,
        "z": 384.627,
        "energy_residual": 100.0,
        "energy_node": 100.0
    },
    {
        "id": 40,
        "x": 36.263,
        "y": 275.066,
        "z": 47.804,
        "energy_residual": 100.0,
        "energy_node": 100.0
    },
    {
        "id": 41,
        "x": 32.2,
        "y": 271.193,
        "z": 80.32,
        "energy_residual": 100.0,
        "energy_node": 100.0
    },
    {
        "id": 42,
        "x": 0.96,
        "y": 265.079,
        "z": 133.009,
        "energy_residual": 100.0,
        "energy_node": 100.0
    },
    {
        "id": 43,
        "x": 14.504,
        "y": 280.901,
        "z": 171.438,
        "energy_residual": 100.0,
        "energy_node": 100.0
    },
    {
        "id": 44,
        "x": 6.774,
        "y": 264.914,
        "z": 228.498,
        "energy_residual": 100.0,
        "energy_node": 100.0
    },
    {
        "id": 45,
        "x": 29.544,
        "y": 278.716,
        "z": 282.66,
        "energy_residual": 100.0,
        "energy_node": 100.0
    },
    {
        "id": 46,
        "x": 32.605,
        "y": 271.571,
        "z": 344.827,
        "energy_residual": 100.0,
        "energy_node": 100.0
    },
    {
        "id": 47,
        "x": 18.378,
        "y": 271.793,
        "z": 394.596,
        "energy_residual": 100.0,
        "energy_node": 100.0
    },
    {
        "id": 48,
        "x": 40.31,
        "y": 335.194,
        "z": 5.011,
        "energy_residual": 100.0,
        "energy_node": 100.0
    },
    {
        "id": 49,
        "x": 45.974,
        "y": 335.712,
        "z": 99.942,
        "energy_residual": 100.0,
        "energy_node": 100.0
    },
    {
        "id": 50,
        "x": 7.472,
        "y": 343.406,
        "z": 108.125,
        "energy_residual": 100.0,
        "energy_node": 100.0
    },
    {
        "id": 51,
        "x": 30.778,
        "y": 306.191,
        "z": 192.4,
        "energy_residual": 100.0,
        "energy_node": 100.0
    },
    {
        "id": 52,
        "x": 40.366,
        "y": 328.455,
        "z": 220.359,
        "energy_residual": 100.0,
        "energy_node": 100.0
    },
    {
        "id": 53,
        "x": 3.458,
        "y": 334.871,
        "z": 272.677,
        "energy_residual": 100.0,
        "energy_node": 100.0
    },
    {
        "id": 54,
        "x": 36.103,
        "y": 343.319,
        "z": 348.776,
        "energy_residual": 100.0,
        "energy_node": 100.0
    },
    {
        "id": 55,
        "x": 42.79,
        "y": 300.586,
        "z": 367.999,
        "energy_residual": 100.0,
        "energy_node": 100.0
    },
    {
        "id": 56,
        "x": 36.5,
        "y": 358.581,
        "z": 26.052,
        "energy_residual": 100.0,
        "energy_node": 100.0
    },
    {
        "id": 57,
        "x": 2.717,
        "y": 360.0,
        "z": 50.926,
        "energy_residual": 100.0,
        "energy_node": 100.0
    },
    {
        "id": 58,
        "x": 39.685,
        "y": 361.196,
        "z": 117.268,
        "energy_residual": 100.0,
        "energy_node": 100.0
    },
    {
        "id": 59,
        "x": 46.404,
        "y": 385.221,
        "z": 151.592,
        "energy_residual": 100.0,
        "energy_node": 100.0
    },
    {
        "id": 60,
        "x": 8.235,
        "y": 381.074,
        "z": 228.861,
        "energy_residual": 100.0,
        "energy_node": 100.0
    },
    {
        "id": 61,
        "x": 11.895,
        "y": 396.711,
        "z": 280.698,
        "energy_residual": 100.0,
        "energy_node": 100.0
    },
    {
        "id": 62,
        "x": 26.782,
        "y": 379.495,
        "z": 336.506,
        "energy_residual": 100.0,
        "energy_node": 100.0
    },
    {
        "id": 63,
        "x": 15.597,
        "y": 369.911,
        "z": 360.492,
        "energy_residual": 100.0,
        "energy_node": 100.0
    },
    {
        "id": 64,
        "x": 59.31,
        "y": 47.219,
        "z": 36.978,
        "energy_residual": 100.0,
        "energy_node": 100.0
    },
    {
        "id": 65,
        "x": 74.523,
        "y": 11.371,
        "z": 62.718,
        "energy_residual": 100.0,
        "energy_node": 100.0
    },
    {
        "id": 66,
        "x": 52.901,
        "y": 21.721,
        "z": 115.59,
        "energy_residual": 100.0,
        "energy_node": 100.0
    },
    {
        "id": 67,
        "x": 84.817,
        "y": 18.888,
        "z": 158.98,
        "energy_residual": 100.0,
        "energy_node": 100.0
    },
    {
        "id": 68,
        "x": 51.234,
        "y": 3.362,
        "z": 233.97,
        "energy_residual": 100.0,
        "energy_node": 100.0
    },
    {
        "id": 69,
        "x": 72.685,
        "y": 26.829,
        "z": 294.834,
        "energy_residual": 100.0,
        "energy_node": 100.0
    },
    {
        "id": 70,
        "x": 99.517,
        "y": 10.845,
        "z": 333.154,
        "energy_residual": 100.0,
        "energy_node": 100.0
    },
    {
        "id": 71,
        "x": 63.166,
        "y": 1.033,
        "z": 387.919,
        "energy_residual": 100.0,
        "energy_node": 100.0
    },
    {
        "id": 72,
        "x": 66.001,
        "y": 69.173,
        "z": 29.416,
        "energy_residual": 100.0,
        "energy_node": 100.0
    },
    {
        "id": 73,
        "x": 91.552,
        "y": 81.449,
        "z": 93.633,
        "energy_residual": 100.0,
        "energy_node": 100.0
    },
    {
        "id": 74,
        "x": 63.677,
        "y": 89.902,
        "z": 109.282,
        "energy_residual": 100.0,
        "energy_node": 100.0
    },
    {
        "id": 75,
        "x": 97.64,
        "y": 84.374,
        "z": 160.775,
        "energy_residual": 100.0,
        "energy_node": 100.0
    },
    {
        "id": 76,
        "x": 97.369,
        "y": 86.543,
        "z": 212.697,
        "energy_residual": 100.0,
        "energy_node": 100.0
    },
    {
        "id": 77,
        "x": 60.666,
        "y": 75.91,
        "z": 251.283,
        "energy_residual": 100.0,
        "energy_node": 100.0
    },
    {
        "id": 78,
        "x": 60.374,
        "y": 71.234,
        "z": 318.708,
        "energy_residual": 100.0,
        "energy_node": 100.0
    },
    {
        "id": 79,
        "x": 73.179,
        "y": 63.881,
        "z": 379.339,
        "energy_residual": 100.0,
        "energy_node": 100.0
    },
    {
        "id": 80,
        "x": 93.193,
        "y": 105.877,
        "z": 25.869,
        "energy_residual": 100.0,
        "energy_node": 100.0
    },
    {
        "id": 81,
        "x": 56.603,
        "y": 135.843,
        "z": 69.803,
        "energy_residual": 100.0,
        "energy_node": 100.0
    },
    {
        "id": 82,
        "x": 78.271,
        "y": 109.164,
        "z": 107.242,
        "energy_residual": 100.0,
        "energy_node": 100.0
    },
    {
        "id": 83,
        "x": 74.403,
        "y": 117.781,
        "z": 197.022,
        "energy_residual": 100.0,
        "energy_node": 100.0
    },
    {
        "id": 84,
        "x": 88.266,
        "y": 137.433,
        "z": 245.186,
        "energy_residual": 100.0,
        "energy_node": 100.0
    },
    {
        "id": 85,
        "x": 54.171,
        "y": 127.61,
        "z": 279.224,
        "energy_residual": 100.0,
        "energy_node": 100.0
    },
    {
        "id": 86,
        "x": 98.097,
        "y": 114.607,
        "z": 312.041,
        "energy_residual": 100.0,
        "energy_node": 100.0
    },
    {
        "id": 87,
        "x": 55.015,
        "y": 100.821,
        "z": 396.476,
        "energy_residual": 100.0,
        "energy_node": 100.0
    },
    {
        "id": 88,
        "x": 83.496,
        "y": 189.258,
        "z": 14.087,
        "energy_residual": 100.0,
        "energy_node": 100.0
    },
    {
        "id": 89,
        "x": 79.321,
        "y": 153.198,
        "z": 74.281,
        "energy_residual": 100.0,
        "energy_node": 100.0
    },
    {
        "id": 90,
        "x": 98.875,
        "y": 193.825,
        "z": 116.908,
        "energy_residual": 100.0,
        "energy_node": 100.0
    },
    {
        "id": 91,
        "x": 98.079,
        "y": 161.585,
        "z": 197.466,
        "energy_residual": 100.0,
        "energy_node": 100.0
    },
    {
        "id": 92,
        "x": 97.069,
        "y": 189.96,
        "z": 231.522,
        "energy_residual": 100.0,
        "energy_node": 100.0
    },
    {
        "id": 93,
        "x": 93.714,
        "y": 164.651,
        "z": 292.447,
        "energy_residual": 100.0,
        "energy_node": 100.0
    },
    {
        "id": 94,
        "x": 80.894,
        "y": 150.662,
        "z": 317.362,
        "energy_residual": 100.0,
        "energy_node": 100.0
    },
    {
        "id": 95,
        "x": 57.407,
        "y": 199.091,
        "z": 373.919,
        "energy_residual": 100.0,
        "energy_node": 100.0
    },
    {
        "id": 96,
        "x": 74.87,
        "y": 231.974,
        "z": 18.429,
        "energy_residual": 100.0,
        "energy_node": 100.0
    },
    {
        "id": 97,
        "x": 56.845,
        "y": 241.106,
        "z": 59.492,
        "energy_residual": 100.0,
        "energy_node": 100.0
    },
    {
        "id": 98,
        "x": 75.566,
        "y": 211.216,
        "z": 104.892,
        "energy_residual": 100.0,
        "energy_node": 100.0
    },
    {
        "id": 99,
        "x": 93.11,
        "y": 248.646,
        "z": 198.042,
        "energy_residual": 100.0,
        "energy_node": 100.0
    },
    {
        "id": 100,
        "x": 95.328,
        "y": 238.702,
        "z": 216.657,
        "energy_residual": 100.0,
        "energy_node": 100.0
    },
    {
        "id": 101,
        "x": 54.055,
        "y": 220.362,
        "z": 261.612,
        "energy_residual": 100.0,
        "energy_node": 100.0
    },
    {
        "id": 102,
        "x": 56.624,
        "y": 202.671,
        "z": 336.28,
        "energy_residual": 100.0,
        "energy_node": 100.0
    },
    {
        "id": 103,
        "x": 50.571,
        "y": 238.529,
        "z": 357.347,
        "energy_residual": 100.0,
        "energy_node": 100.0
    },
    {
        "id": 104,
        "x": 53.976,
        "y": 254.48,
        "z": 33.602,
        "energy_residual": 100.0,
        "energy_node": 100.0
    },
    {
        "id": 105,
        "x": 62.268,
        "y": 271.027,
        "z": 77.868,
        "energy_residual": 100.0,
        "energy_node": 100.0
    },
    {
        "id": 106,
        "x": 93.028,
        "y": 286.352,
        "z": 113.516,
        "energy_residual": 100.0,
        "energy_node": 100.0
    },
    {
        "id": 107,
        "x": 56.574,
        "y": 252.769,
        "z": 165.08,
        "energy_residual": 100.0,
        "energy_node": 100.0
    },
    {
        "id": 108,
        "x": 63.106,
        "y": 272.807,
        "z": 234.164,
        "energy_residual": 100.0,
        "energy_node": 100.0
    },
    {
        "id": 109,
        "x": 84.781,
        "y": 264.176,
        "z": 268.996,
        "energy_residual": 100.0,
        "energy_node": 100.0
    },
    {
        "id": 110,
        "x": 59.058,
        "y": 289.427,
        "z": 302.842,
        "energy_residual": 100.0,
        "energy_node": 100.0
    },
    {
        "id": 111,
        "x": 84.85,
        "y": 288.935,
        "z": 388.87,
        "energy_residual": 100.0,
        "energy_node": 100.0
    },
    {
        "id": 112,
        "x": 62.971,
        "y": 318.691,
        "z": 29.38,
        "energy_residual": 100.0,
        "energy_node": 100.0
    },
    {
        "id": 113,
        "x": 63.641,
        "y": 318.543,
        "z": 59.853,
        "energy_residual": 100.0,
        "energy_node": 100.0
    },
    {
        "id": 114,
        "x": 72.993,
        "y": 302.231,
        "z": 139.99,
        "energy_residual": 100.0,
        "energy_node": 100.0
    },
    {
        "id": 115,
        "x": 53.848,
        "y": 325.942,
        "z": 165.341,
        "energy_residual": 100.0,
        "energy_node": 100.0
    },
    {
        "id": 116,
        "x": 78.877,
        "y": 347.972,
        "z": 232.279,
        "energy_residual": 100.0,
        "energy_node": 100.0
    },
    {
        "id": 117,
        "x": 51.768,
        "y": 321.52,
        "z": 275.501,
        "energy_residual": 100.0,
        "energy_node": 100.0
    },
    {
        "id": 118,
        "x": 76.809,
        "y": 334.07,
        "z": 313.88,
        "energy_residual": 100.0,
        "energy_node": 100.0
    },
    {
        "id": 119,
        "x": 56.443,
        "y": 319.634,
        "z": 397.82,
        "energy_residual": 100.0,
        "energy_node": 100.0
    },
    {
        "id": 120,
        "x": 59.357,
        "y": 395.199,
        "z": 27.19,
        "energy_residual": 100.0,
        "energy_node": 100.0
    },
    {
        "id": 121,
        "x": 72.846,
        "y": 394.102,
        "z": 72.93,
        "energy_residual": 100.0,
        "energy_node": 100.0
    },
    {
        "id": 122,
        "x": 86.208,
        "y": 369.951,
        "z": 145.202,
        "energy_residual": 100.0,
        "energy_node": 100.0
    },
    {
        "id": 123,
        "x": 84.501,
        "y": 384.981,
        "z": 166.386,
        "energy_residual": 100.0,
        "energy_node": 100.0
    },
    {
        "id": 124,
        "x": 87.839,
        "y": 381.803,
        "z": 212.001,
        "energy_residual": 100.0,
        "energy_node": 100.0
    },
    {
        "id": 125,
        "x": 58.027,
        "y": 389.82,
        "z": 297.958,
        "energy_residual": 100.0,
        "energy_node": 100.0
    },
    {
        "id": 126,
        "x": 72.907,
        "y": 379.549,
        "z": 342.886,
        "energy_residual": 100.0,
        "energy_node": 100.0
    },
    {
        "id": 127,
        "x": 72.861,
        "y": 397.594,
        "z": 378.788,
        "energy_residual": 100.0,
        "energy_node": 100.0
    },
    {
        "id": 128,
        "x": 141.038,
        "y": 45.442,
        "z": 40.776,
        "energy_residual": 100.0,
        "energy_node": 100.0
    },
    {
        "id": 129,
        "x": 107.971,
        "y": 31.445,
        "z": 69.922,
        "energy_residual": 100.0,
        "energy_node": 100.0
    },
    {
        "id": 130,
        "x": 103.136,
        "y": 21.202,
        "z": 112.934,
        "energy_residual": 100.0,
        "energy_node": 100.0
    },
    {
        "id": 131,
        "x": 142.452,
        "y": 1.665,
        "z": 197.949,
        "energy_residual": 100.0,
        "energy_node": 100.0
    },
    {
        "id": 132,
        "x": 117.768,
        "y": 17.835,
        "z": 200.816,
        "energy_residual": 100.0,
        "energy_node": 100.0
    },
    {
        "id": 133,
        "x": 109.262,
        "y": 20.063,
        "z": 296.465,
        "energy_residual": 100.0,
        "energy_node": 100.0
    },
    {
        "id": 134,
        "x": 104.981,
        "y": 47.265,
        "z": 343.474,
        "energy_residual": 100.0,
        "energy_node": 100.0
    },
    {
        "id": 135,
        "x": 122.708,
        "y": 16.335,
        "z": 361.637,
        "energy_residual": 100.0,
        "energy_node": 100.0
    },
    {
        "id": 136,
        "x": 130.723,
        "y": 51.654,
        "z": 0.78,
        "energy_residual": 100.0,
        "energy_node": 100.0
    },
    {
        "id": 137,
        "x": 121.44,
        "y": 53.404,
        "z": 62.597,
        "energy_residual": 100.0,
        "energy_node": 100.0
    },
    {
        "id": 138,
        "x": 111.058,
        "y": 62.66,
        "z": 106.553,
        "energy_residual": 100.0,
        "energy_node": 100.0
    },
    {
        "id": 139,
        "x": 100.602,
        "y": 55.774,
        "z": 180.924,
        "energy_residual": 100.0,
        "energy_node": 100.0
    },
    {
        "id": 140,
        "x": 148.713,
        "y": 99.517,
        "z": 220.453,
        "energy_residual": 100.0,
        "energy_node": 100.0
    },
    {
        "id": 141,
        "x": 108.148,
        "y": 81.938,
        "z": 274.515,
        "energy_residual": 100.0,
        "energy_node": 100.0
    },
    {
        "id": 142,
        "x": 149.47,
        "y": 53.265,
        "z": 339.162,
        "energy_residual": 100.0,
        "energy_node": 100.0
    },
    {
        "id": 143,
        "x": 114.42,
        "y": 62.071,
        "z": 383.125,
        "energy_residual": 100.0,
        "energy_node": 100.0
    },
    {
        "id": 144,
        "x": 112.303,
        "y": 133.293,
        "z": 25.865,
        "energy_residual": 100.0,
        "energy_node": 100.0
    },
    {
        "id": 145,
        "x": 121.204,
        "y": 127.734,
        "z": 64.353,
        "energy_residual": 100.0,
        "energy_node": 100.0
    },
    {
        "id": 146,
        "x": 135.329,
        "y": 120.743,
        "z": 118.027,
        "energy_residual": 100.0,
        "energy_node": 100.0
    },
    {
        "id": 147,
        "x": 141.433,
        "y": 146.248,
        "z": 152.3,
        "energy_residual": 100.0,
        "energy_node": 100.0
    },
    {
        "id": 148,
        "x": 111.631,
        "y": 117.426,
        "z": 240.748,
        "energy_residual": 100.0,
        "energy_node": 100.0
    },
    {
        "id": 149,
        "x": 149.275,
        "y": 148.449,
        "z": 295.247,
        "energy_residual": 100.0,
        "energy_node": 100.0
    },
    {
        "id": 150,
        "x": 114.828,
        "y": 149.601,
        "z": 312.471,
        "energy_residual": 100.0,
        "energy_node": 100.0
    },
    {
        "id": 151,
        "x": 105.295,
        "y": 147.548,
        "z": 361.671,
        "energy_residual": 100.0,
        "energy_node": 100.0
    },
    {
        "id": 152,
        "x": 134.488,
        "y": 152.918,
        "z": 36.535,
        "energy_residual": 100.0,
        "energy_node": 100.0
    },
    {
        "id": 153,
        "x": 144.086,
        "y": 163.622,
        "z": 68.953,
        "energy_residual": 100.0,
        "energy_node": 100.0
    },
    {
        "id": 154,
        "x": 118.715,
        "y": 187.439,
        "z": 111.89,
        "energy_residual": 100.0,
        "energy_node": 100.0
    },
    {
        "id": 155,
        "x": 108.593,
        "y": 172.465,
        "z": 165.223,
        "energy_residual": 100.0,
        "energy_node": 100.0
    },
    {
        "id": 156,
        "x": 141.959,
        "y": 161.887,
        "z": 225.119,
        "energy_residual": 100.0,
        "energy_node": 100.0
    },
    {
        "id": 157,
        "x": 147.129,
        "y": 181.7,
        "z": 293.364,
        "energy_residual": 100.0,
        "energy_node": 100.0
    },
    {
        "id": 158,
        "x": 147.01,
        "y": 187.538,
        "z": 334.979,
        "energy_residual": 100.0,
        "energy_node": 100.0
    },
    {
        "id": 159,
        "x": 148.398,
        "y": 199.72,
        "z": 372.591,
        "energy_residual": 100.0,
        "energy_node": 100.0
    },
    {
        "id": 160,
        "x": 103.543,
        "y": 214.64,
        "z": 7.618,
        "energy_residual": 100.0,
        "energy_node": 100.0
    },
    {
        "id": 161,
        "x": 120.874,
        "y": 206.564,
        "z": 80.206,
        "energy_residual": 100.0,
        "energy_node": 100.0
    },
    {
        "id": 162,
        "x": 119.14,
        "y": 244.769,
        "z": 148.39,
        "energy_residual": 100.0,
        "energy_node": 100.0
    },
    {
        "id": 163,
        "x": 127.344,
        "y": 213.741,
        "z": 179.612,
        "energy_residual": 100.0,
        "energy_node": 100.0
    },
    {
        "id": 164,
        "x": 144.838,
        "y": 220.337,
        "z": 227.604,
        "energy_residual": 100.0,
        "energy_node": 100.0
    },
    {
        "id": 165,
        "x": 113.583,
        "y": 222.772,
        "z": 270.086,
        "energy_residual": 100.0,
        "energy_node": 100.0
    },
    {
        "id": 166,
        "x": 112.421,
        "y": 225.293,
        "z": 315.519,
        "energy_residual": 100.0,
        "energy_node": 100.0
    },
    {
        "id": 167,
        "x": 118.652,
        "y": 226.249,
        "z": 387.53,
        "energy_residual": 100.0,
        "energy_node": 100.0
    },
    {
        "id": 168,
        "x": 116.675,
        "y": 296.208,
        "z": 43.116,
        "energy_residual": 100.0,
        "energy_node": 100.0
    },
    {
        "id": 169,
        "x": 102.435,
        "y": 262.682,
        "z": 72.307,
        "energy_residual": 100.0,
        "energy_node": 100.0
    },
    {
        "id": 170,
        "x": 105.231,
        "y": 267.424,
        "z": 137.005,
        "energy_residual": 100.0,
        "energy_node": 100.0
    },
    {
        "id": 171,
        "x": 134.026,
        "y": 281.119,
        "z": 185.526,
        "energy_residual": 100.0,
        "energy_node": 100.0
    },
    {
        "id": 172,
        "x": 110.246,
        "y": 267.085,
        "z": 233.812,
        "energy_residual": 100.0,
        "energy_node": 100.0
    },
    {
        "id": 173,
        "x": 143.962,
        "y": 277.184,
        "z": 264.135,
        "energy_residual": 100.0,
        "energy_node": 100.0
    },
    {
        "id": 174,
        "x": 101.512,
        "y": 285.517,
        "z": 300.394,
        "energy_residual": 100.0,
        "energy_node": 100.0
    },
    {
        "id": 175,
        "x": 118.634,
        "y": 276.527,
        "z": 396.106,
        "energy_residual": 100.0,
        "energy_node": 100.0
    },
    {
        "id": 176,
        "x": 104.475,
        "y": 320.297,
        "z": 1.216,
        "energy_residual": 100.0,
        "energy_node": 100.0
    },
    {
        "id": 177,
        "x": 117.131,
        "y": 331.112,
        "z": 63.953,
        "energy_residual": 100.0,
        "energy_node": 100.0
    },
    {
        "id": 178,
        "x": 110.487,
        "y": 305.785,
        "z": 128.857,
        "energy_residual": 100.0,
        "energy_node": 100.0
    },
    {
        "id": 179,
        "x": 134.764,
        "y": 333.598,
        "z": 197.443,
        "energy_residual": 100.0,
        "energy_node": 100.0
    },
    {
        "id": 180,
        "x": 100.135,
        "y": 332.36,
        "z": 230.02,
        "energy_residual": 100.0,
        "energy_node": 100.0
    },
    {
        "id": 181,
        "x": 129.437,
        "y": 348.139,
        "z": 250.844,
        "energy_residual": 100.0,
        "energy_node": 100.0
    },
    {
        "id": 182,
        "x": 134.824,
        "y": 340.684,
        "z": 325.49,
        "energy_residual": 100.0,
        "energy_node": 100.0
    },
    {
        "id": 183,
        "x": 116.698,
        "y": 339.542,
        "z": 354.862,
        "energy_residual": 100.0,
        "energy_node": 100.0
    },
    {
        "id": 184,
        "x": 122.102,
        "y": 375.998,
        "z": 34.698,
        "energy_residual": 100.0,
        "energy_node": 100.0
    },
    {
        "id": 185,
        "x": 104.544,
        "y": 361.388,
        "z": 70.515,
        "energy_residual": 100.0,
        "energy_node": 100.0
    },
    {
        "id": 186,
        "x": 131.165,
        "y": 394.348,
        "z": 130.941,
        "energy_residual": 100.0,
        "energy_node": 100.0
    },
    {
        "id": 187,
        "x": 106.673,
        "y": 399.029,
        "z": 193.589,
        "energy_residual": 100.0,
        "energy_node": 100.0
    },
    {
        "id": 188,
        "x": 125.136,
        "y": 396.117,
        "z": 227.069,
        "energy_residual": 100.0,
        "energy_node": 100.0
    },
    {
        "id": 189,
        "x": 146.165,
        "y": 391.495,
        "z": 298.414,
        "energy_residual": 100.0,
        "energy_node": 100.0
    },
    {
        "id": 190,
        "x": 145.989,
        "y": 351.802,
        "z": 308.739,
        "energy_residual": 100.0,
        "energy_node": 100.0
    },
    {
        "id": 191,
        "x": 119.457,
        "y": 397.607,
        "z": 365.001,
        "energy_residual": 100.0,
        "energy_node": 100.0
    },
    {
        "id": 192,
        "x": 158.023,
        "y": 44.315,
        "z": 22.32,
        "energy_residual": 100.0,
        "energy_node": 100.0
    },
    {
        "id": 193,
        "x": 195.394,
        "y": 8.012,
        "z": 83.056,
        "energy_residual": 100.0,
        "energy_node": 100.0
    },
    {
        "id": 194,
        "x": 172.013,
        "y": 3.824,
        "z": 134.823,
        "energy_residual": 100.0,
        "energy_node": 100.0
    },
    {
        "id": 195,
        "x": 162.37,
        "y": 1.981,
        "z": 152.997,
        "energy_residual": 100.0,
        "energy_node": 100.0
    },
    {
        "id": 196,
        "x": 153.054,
        "y": 45.387,
        "z": 236.994,
        "energy_residual": 100.0,
        "energy_node": 100.0
    },
    {
        "id": 197,
        "x": 194.903,
        "y": 33.629,
        "z": 276.447,
        "energy_residual": 100.0,
        "energy_node": 100.0
    },
    {
        "id": 198,
        "x": 165.222,
        "y": 49.898,
        "z": 318.109,
        "energy_residual": 100.0,
        "energy_node": 100.0
    },
    {
        "id": 199,
        "x": 173.532,
        "y": 18.912,
        "z": 398.976,
        "energy_residual": 100.0,
        "energy_node": 100.0
    },
    {
        "id": 200,
        "x": 158.733,
        "y": 66.399,
        "z": 34.017,
        "energy_residual": 100.0,
        "energy_node": 100.0
    },
    {
        "id": 201,
        "x": 153.16,
        "y": 80.362,
        "z": 73.882,
        "energy_residual": 100.0,
        "energy_node": 100.0
    },
    {
        "id": 202,
        "x": 164.2,
        "y": 61.921,
        "z": 125.726,
        "energy_residual": 100.0,
        "energy_node": 100.0
    },
    {
        "id": 203,
        "x": 168.396,
        "y": 72.826,
        "z": 166.874,
        "energy_residual": 100.0,
        "energy_node": 100.0
    },
    {
        "id": 204,
        "x": 198.525,
        "y": 56.672,
        "z": 204.84,
        "energy_residual": 100.0,
        "energy_node": 100.0
    },
    {
        "id": 205,
        "x": 167.17,
        "y": 79.551,
        "z": 282.959,
        "energy_residual": 100.0,
        "energy_node": 100.0
    },
    {
        "id": 206,
        "x": 169.863,
        "y": 99.964,
        "z": 317.595,
        "energy_residual": 100.0,
        "energy_node": 100.0
    },
    {
        "id": 207,
        "x": 186.07,
        "y": 81.879,
        "z": 390.653,
        "energy_residual": 100.0,
        "energy_node": 100.0
    },
    {
        "id": 208,
        "x": 198.811,
        "y": 144.49,
        "z": 38.228,
        "energy_residual": 100.0,
        "energy_node": 100.0
    },
    {
        "id": 209,
        "x": 184.912,
        "y": 116.775,
        "z": 57.384,
        "energy_residual": 100.0,
        "energy_node": 100.0
    },
    {
        "id": 210,
        "x": 153.132,
        "y": 112.095,
        "z": 121.614,
        "energy_residual": 100.0,
        "energy_node": 100.0
    },
    {
        "id": 211,
        "x": 176.1,
        "y": 138.654,
        "z": 197.937,
        "energy_residual": 100.0,
        "energy_node": 100.0
    },
    {
        "id": 212,
        "x": 155.866,
        "y": 105.35,
        "z": 229.485,
        "energy_residual": 100.0,
        "energy_node": 100.0
    },
    {
        "id": 213,
        "x": 187.27,
        "y": 142.408,
        "z": 296.792,
        "energy_residual": 100.0,
        "energy_node": 100.0
    },
    {
        "id": 214,
        "x": 199.171,
        "y": 119.99,
        "z": 319.017,
        "energy_residual": 100.0,
        "energy_node": 100.0
    },
    {
        "id": 215,
        "x": 157.39,
        "y": 134.247,
        "z": 382.838,
        "energy_residual": 100.0,
        "energy_node": 100.0
    },
    {
        "id": 216,
        "x": 193.103,
        "y": 154.863,
        "z": 24.889,
        "energy_residual": 100.0,
        "energy_node": 100.0
    },
    {
        "id": 217,
        "x": 179.054,
        "y": 162.078,
        "z": 58.451,
        "energy_residual": 100.0,
        "energy_node": 100.0
    },
    {
        "id": 218,
        "x": 192.979,
        "y": 152.927,
        "z": 123.531,
        "energy_residual": 100.0,
        "energy_node": 100.0
    },
    {
        "id": 219,
        "x": 155.792,
        "y": 172.853,
        "z": 198.998,
        "energy_residual": 100.0,
        "energy_node": 100.0
    },
    {
        "id": 220,
        "x": 171.185,
        "y": 192.856,
        "z": 205.866,
        "energy_residual": 100.0,
        "energy_node": 100.0
    },
    {
        "id": 221,
        "x": 163.563,
        "y": 170.19,
        "z": 269.991,
        "energy_residual": 100.0,
        "energy_node": 100.0
    },
    {
        "id": 222,
        "x": 183.569,
        "y": 167.236,
        "z": 335.688,
        "energy_residual": 100.0,
        "energy_node": 100.0
    },
    {
        "id": 223,
        "x": 181.959,
        "y": 169.958,
        "z": 371.588,
        "energy_residual": 100.0,
        "energy_node": 100.0
    },
    {
        "id": 224,
        "x": 180.726,
        "y": 203.502,
        "z": 41.12,
        "energy_residual": 100.0,
        "energy_node": 100.0
    },
    {
        "id": 225,
        "x": 182.671,
        "y": 236.317,
        "z": 76.846,
        "energy_residual": 100.0,
        "energy_node": 100.0
    },
    {
        "id": 226,
        "x": 155.524,
        "y": 220.252,
        "z": 120.269,
        "energy_residual": 100.0,
        "energy_node": 100.0
    },
    {
        "id": 227,
        "x": 166.052,
        "y": 201.498,
        "z": 186.863,
        "energy_residual": 100.0,
        "energy_node": 100.0
    },
    {
        "id": 228,
        "x": 155.489,
        "y": 230.315,
        "z": 235.161,
        "energy_residual": 100.0,
        "energy_node": 100.0
    },
    {
        "id": 229,
        "x": 181.739,
        "y": 247.957,
        "z": 255.165,
        "energy_residual": 100.0,
        "energy_node": 100.0
    },
    {
        "id": 230,
        "x": 193.358,
        "y": 201.46,
        "z": 326.746,
        "energy_residual": 100.0,
        "energy_node": 100.0
    },
    {
        "id": 231,
        "x": 170.212,
        "y": 226.209,
        "z": 368.255,
        "energy_residual": 100.0,
        "energy_node": 100.0
    },
    {
        "id": 232,
        "x": 159.528,
        "y": 250.956,
        "z": 25.907,
        "energy_residual": 100.0,
        "energy_node": 100.0
    },
    {
        "id": 233,
        "x": 192.139,
        "y": 268.661,
        "z": 61.143,
        "energy_residual": 100.0,
        "energy_node": 100.0
    },
    {
        "id": 234,
        "x": 154.027,
        "y": 254.266,
        "z": 111.07,
        "energy_residual": 100.0,
        "energy_node": 100.0
    },
    {
        "id": 235,
        "x": 155.001,
        "y": 263.252,
        "z": 153.307,
        "energy_residual": 100.0,
        "energy_node": 100.0
    },
    {
        "id": 236,
        "x": 153.28,
        "y": 292.814,
        "z": 208.106,
        "energy_residual": 100.0,
        "energy_node": 100.0
    },
    {
        "id": 237,
        "x": 177.984,
        "y": 288.673,
        "z": 272.82,
        "energy_residual": 100.0,
        "energy_node": 100.0
    },
    {
        "id": 238,
        "x": 157.668,
        "y": 259.98,
        "z": 321.649,
        "energy_residual": 100.0,
        "energy_node": 100.0
    },
    {
        "id": 239,
        "x": 176.412,
        "y": 267.472,
        "z": 389.074,
        "energy_residual": 100.0,
        "energy_node": 100.0
    },
    {
        "id": 240,
        "x": 187.551,
        "y": 346.361,
        "z": 1.448,
        "energy_residual": 100.0,
        "energy_node": 100.0
    },
    {
        "id": 241,
        "x": 194.785,
        "y": 319.628,
        "z": 93.919,
        "energy_residual": 100.0,
        "energy_node": 100.0
    },
    {
        "id": 242,
        "x": 184.539,
        "y": 349.367,
        "z": 137.964,
        "energy_residual": 100.0,
        "energy_node": 100.0
    },
    {
        "id": 243,
        "x": 168.227,
        "y": 325.053,
        "z": 168.819,
        "energy_residual": 100.0,
        "energy_node": 100.0
    },
    {
        "id": 244,
        "x": 168.246,
        "y": 313.045,
        "z": 224.799,
        "energy_residual": 100.0,
        "energy_node": 100.0
    },
    {
        "id": 245,
        "x": 184.087,
        "y": 313.867,
        "z": 276.219,
        "energy_residual": 100.0,
        "energy_node": 100.0
    },
    {
        "id": 246,
        "x": 155.869,
        "y": 307.992,
        "z": 302.34,
        "energy_residual": 100.0,
        "energy_node": 100.0
    },
    {
        "id": 247,
        "x": 198.537,
        "y": 300.193,
        "z": 358.929,
        "energy_residual": 100.0,
        "energy_node": 100.0
    },
    {
        "id": 248,
        "x": 180.643,
        "y": 354.068,
        "z": 44.095,
        "energy_residual": 100.0,
        "energy_node": 100.0
    },
    {
        "id": 249,
        "x": 185.981,
        "y": 398.319,
        "z": 75.382,
        "energy_residual": 100.0,
        "energy_node": 100.0
    },
    {
        "id": 250,
        "x": 165.02,
        "y": 377.475,
        "z": 146.541,
        "energy_residual": 100.0,
        "energy_node": 100.0
    },
    {
        "id": 251,
        "x": 176.038,
        "y": 363.36,
        "z": 193.87,
        "energy_residual": 100.0,
        "energy_node": 100.0
    },
    {
        "id": 252,
        "x": 168.596,
        "y": 350.069,
        "z": 212.384,
        "energy_residual": 100.0,
        "energy_node": 100.0
    },
    {
        "id": 253,
        "x": 165.912,
        "y": 392.939,
        "z": 272.925,
        "energy_residual": 100.0,
        "energy_node": 100.0
    },
    {
        "id": 254,
        "x": 172.229,
        "y": 366.805,
        "z": 344.034,
        "energy_residual": 100.0,
        "energy_node": 100.0
    },
    {
        "id": 255,
        "x": 197.251,
        "y": 399.595,
        "z": 368.837,
        "energy_residual": 100.0,
        "energy_node": 100.0
    },
    {
        "id": 256,
        "x": 248.307,
        "y": 39.594,
        "z": 33.784,
        "energy_residual": 100.0,
        "energy_node": 100.0
    },
    {
        "id": 257,
        "x": 212.244,
        "y": 10.823,
        "z": 58.302,
        "energy_residual": 100.0,
        "energy_node": 100.0
    },
    {
        "id": 258,
        "x": 246.138,
        "y": 14.704,
        "z": 122.655,
        "energy_residual": 100.0,
        "energy_node": 100.0
    },
    {
        "id": 259,
        "x": 224.698,
        "y": 38.909,
        "z": 192.212,
        "energy_residual": 100.0,
        "energy_node": 100.0
    },
    {
        "id": 260,
        "x": 206.954,
        "y": 21.345,
        "z": 242.143,
        "energy_residual": 100.0,
        "energy_node": 100.0
    },
    {
        "id": 261,
        "x": 240.902,
        "y": 5.121,
        "z": 257.819,
        "energy_residual": 100.0,
        "energy_node": 100.0
    },
    {
        "id": 262,
        "x": 215.21,
        "y": 3.768,
        "z": 321.233,
        "energy_residual": 100.0,
        "energy_node": 100.0
    },
    {
        "id": 263,
        "x": 205.381,
        "y": 28.411,
        "z": 362.328,
        "energy_residual": 100.0,
        "energy_node": 100.0
    },
    {
        "id": 264,
        "x": 229.822,
        "y": 55.876,
        "z": 48.794,
        "energy_residual": 100.0,
        "energy_node": 100.0
    },
    {
        "id": 265,
        "x": 246.628,
        "y": 69.59,
        "z": 62.109,
        "energy_residual": 100.0,
        "energy_node": 100.0
    },
    {
        "id": 266,
        "x": 212.52,
        "y": 74.17,
        "z": 102.0,
        "energy_residual": 100.0,
        "energy_node": 100.0
    },
    {
        "id": 267,
        "x": 231.985,
        "y": 70.415,
        "z": 168.87,
        "energy_residual": 100.0,
        "energy_node": 100.0
    },
    {
        "id": 268,
        "x": 240.468,
        "y": 85.452,
        "z": 247.717,
        "energy_residual": 100.0,
        "energy_node": 100.0
    },
    {
        "id": 269,
        "x": 217.597,
        "y": 94.877,
        "z": 288.498,
        "energy_residual": 100.0,
        "energy_node": 100.0
    },
    {
        "id": 270,
        "x": 217.871,
        "y": 81.083,
        "z": 314.428,
        "energy_residual": 100.0,
        "energy_node": 100.0
    },
    {
        "id": 271,
        "x": 243.72,
        "y": 55.621,
        "z": 360.622,
        "energy_residual": 100.0,
        "energy_node": 100.0
    },
    {
        "id": 272,
        "x": 209.152,
        "y": 120.151,
        "z": 37.262,
        "energy_residual": 100.0,
        "energy_node": 100.0
    },
    {
        "id": 273,
        "x": 226.345,
        "y": 124.384,
        "z": 50.027,
        "energy_residual": 100.0,
        "energy_node": 100.0
    },
    {
        "id": 274,
        "x": 221.27,
        "y": 103.178,
        "z": 110.413,
        "energy_residual": 100.0,
        "energy_node": 100.0
    },
    {
        "id": 275,
        "x": 246.62,
        "y": 110.77,
        "z": 192.917,
        "energy_residual": 100.0,
        "energy_node": 100.0
    },
    {
        "id": 276,
        "x": 240.145,
        "y": 107.957,
        "z": 230.286,
        "energy_residual": 100.0,
        "energy_node": 100.0
    },
    {
        "id": 277,
        "x": 205.783,
        "y": 136.394,
        "z": 281.873,
        "energy_residual": 100.0,
        "energy_node": 100.0
    },
    {
        "id": 278,
        "x": 240.597,
        "y": 123.969,
        "z": 345.743,
        "energy_residual": 100.0,
        "energy_node": 100.0
    },
    {
        "id": 279,
        "x": 202.467,
        "y": 114.644,
        "z": 385.753,
        "energy_residual": 100.0,
        "energy_node": 100.0
    },
    {
        "id": 280,
        "x": 220.905,
        "y": 158.648,
        "z": 5.361,
        "energy_residual": 100.0,
        "energy_node": 100.0
    },
    {
        "id": 281,
        "x": 240.867,
        "y": 173.657,
        "z": 94.114,
        "energy_residual": 100.0,
        "energy_node": 100.0
    },
    {
        "id": 282,
        "x": 236.664,
        "y": 170.486,
        "z": 118.676,
        "energy_residual": 100.0,
        "energy_node": 100.0
    },
    {
        "id": 283,
        "x": 225.782,
        "y": 194.453,
        "z": 186.864,
        "energy_residual": 100.0,
        "energy_node": 100.0
    },
    {
        "id": 284,
        "x": 200.258,
        "y": 184.708,
        "z": 245.975,
        "energy_residual": 100.0,
        "energy_node": 100.0
    },
    {
        "id": 285,
        "x": 235.523,
        "y": 158.85,
        "z": 274.176,
        "energy_residual": 100.0,
        "energy_node": 100.0
    },
    {
        "id": 286,
        "x": 207.016,
        "y": 167.95,
        "z": 346.856,
        "energy_residual": 100.0,
        "energy_node": 100.0
    },
    {
        "id": 287,
        "x": 246.165,
        "y": 164.142,
        "z": 366.982,
        "energy_residual": 100.0,
        "energy_node": 100.0
    },
    {
        "id": 288,
        "x": 230.011,
        "y": 248.16,
        "z": 7.39,
        "energy_residual": 100.0,
        "energy_node": 100.0
    },
    {
        "id": 289,
        "x": 212.846,
        "y": 243.678,
        "z": 74.595,
        "energy_residual": 100.0,
        "energy_node": 100.0
    },
    {
        "id": 290,
        "x": 244.948,
        "y": 209.276,
        "z": 126.633,
        "energy_residual": 100.0,
        "energy_node": 100.0
    },
    {
        "id": 291,
        "x": 216.313,
        "y": 215.827,
        "z": 172.344,
        "energy_residual": 100.0,
        "energy_node": 100.0
    },
    {
        "id": 292,
        "x": 221.654,
        "y": 217.867,
        "z": 245.749,
        "energy_residual": 100.0,
        "energy_node": 100.0
    },
    {
        "id": 293,
        "x": 236.587,
        "y": 236.377,
        "z": 264.496,
        "energy_residual": 100.0,
        "energy_node": 100.0
    },
    {
        "id": 294,
        "x": 228.885,
        "y": 238.959,
        "z": 339.78,
        "energy_residual": 100.0,
        "energy_node": 100.0
    },
    {
        "id": 295,
        "x": 217.227,
        "y": 238.544,
        "z": 386.795,
        "energy_residual": 100.0,
        "energy_node": 100.0
    },
    {
        "id": 296,
        "x": 207.075,
        "y": 293.297,
        "z": 22.066,
        "energy_residual": 100.0,
        "energy_node": 100.0
    },
    {
        "id": 297,
        "x": 224.321,
        "y": 272.418,
        "z": 78.392,
        "energy_residual": 100.0,
        "energy_node": 100.0
    },
    {
        "id": 298,
        "x": 231.058,
        "y": 274.909,
        "z": 143.339,
        "energy_residual": 100.0,
        "energy_node": 100.0
    },
    {
        "id": 299,
        "x": 231.387,
        "y": 270.071,
        "z": 170.835,
        "energy_residual": 100.0,
        "energy_node": 100.0
    },
    {
        "id": 300,
        "x": 240.542,
        "y": 267.41,
        "z": 210.573,
        "energy_residual": 100.0,
        "energy_node": 100.0
    },
    {
        "id": 301,
        "x": 202.969,
        "y": 293.801,
        "z": 295.927,
        "energy_residual": 100.0,
        "energy_node": 100.0
    },
    {
        "id": 302,
        "x": 206.006,
        "y": 266.724,
        "z": 308.769,
        "energy_residual": 100.0,
        "energy_node": 100.0
    },
    {
        "id": 303,
        "x": 205.795,
        "y": 294.993,
        "z": 352.844,
        "energy_residual": 100.0,
        "energy_node": 100.0
    },
    {
        "id": 304,
        "x": 249.024,
        "y": 304.823,
        "z": 43.174,
        "energy_residual": 100.0,
        "energy_node": 100.0
    },
    {
        "id": 305,
        "x": 228.325,
        "y": 318.396,
        "z": 67.117,
        "energy_residual": 100.0,
        "energy_node": 100.0
    },
    {
        "id": 306,
        "x": 237.868,
        "y": 315.729,
        "z": 132.866,
        "energy_residual": 100.0,
        "energy_node": 100.0
    },
    {
        "id": 307,
        "x": 225.866,
        "y": 324.248,
        "z": 195.058,
        "energy_residual": 100.0,
        "energy_node": 100.0
    },
    {
        "id": 308,
        "x": 227.732,
        "y": 341.343,
        "z": 236.279,
        "energy_residual": 100.0,
        "energy_node": 100.0
    },
    {
        "id": 309,
        "x": 201.928,
        "y": 338.656,
        "z": 260.844,
        "energy_residual": 100.0,
        "energy_node": 100.0
    },
    {
        "id": 310,
        "x": 245.157,
        "y": 302.146,
        "z": 316.654,
        "energy_residual": 100.0,
        "energy_node": 100.0
    },
    {
        "id": 311,
        "x": 204.987,
        "y": 323.779,
        "z": 391.001,
        "energy_residual": 100.0,
        "energy_node": 100.0
    },
    {
        "id": 312,
        "x": 214.909,
        "y": 357.547,
        "z": 16.513,
        "energy_residual": 100.0,
        "energy_node": 100.0
    },
    {
        "id": 313,
        "x": 240.694,
        "y": 357.019,
        "z": 61.368,
        "energy_residual": 100.0,
        "energy_node": 100.0
    },
    {
        "id": 314,
        "x": 203.443,
        "y": 385.286,
        "z": 119.762,
        "energy_residual": 100.0,
        "energy_node": 100.0
    },
    {
        "id": 315,
        "x": 215.542,
        "y": 385.931,
        "z": 166.799,
        "energy_residual": 100.0,
        "energy_node": 100.0
    },
    {
        "id": 316,
        "x": 236.389,
        "y": 390.76,
        "z": 210.883,
        "energy_residual": 100.0,
        "energy_node": 100.0
    },
    {
        "id": 317,
        "x": 248.691,
        "y": 358.118,
        "z": 264.542,
        "energy_residual": 100.0,
        "energy_node": 100.0
    },
    {
        "id": 318,
        "x": 208.99,
        "y": 367.275,
        "z": 324.003,
        "energy_residual": 100.0,
        "energy_node": 100.0
    },
    {
        "id": 319,
        "x": 226.109,
        "y": 392.68,
        "z": 394.472,
        "energy_residual": 100.0,
        "energy_node": 100.0
    },
    {
        "id": 320,
        "x": 261.005,
        "y": 31.145,
        "z": 5.575,
        "energy_residual": 100.0,
        "energy_node": 100.0
    },
    {
        "id": 321,
        "x": 272.948,
        "y": 16.117,
        "z": 65.825,
        "energy_residual": 100.0,
        "energy_node": 100.0
    },
    {
        "id": 322,
        "x": 274.129,
        "y": 36.491,
        "z": 103.459,
        "energy_residual": 100.0,
        "energy_node": 100.0
    },
    {
        "id": 323,
        "x": 293.959,
        "y": 36.741,
        "z": 158.825,
        "energy_residual": 100.0,
        "energy_node": 100.0
    },
    {
        "id": 324,
        "x": 296.958,
        "y": 25.316,
        "z": 249.99,
        "energy_residual": 100.0,
        "energy_node": 100.0
    },
    {
        "id": 325,
        "x": 259.863,
        "y": 26.745,
        "z": 264.512,
        "energy_residual": 100.0,
        "energy_node": 100.0
    },
    {
        "id": 326,
        "x": 265.209,
        "y": 29.553,
        "z": 346.086,
        "energy_residual": 100.0,
        "energy_node": 100.0
    },
    {
        "id": 327,
        "x": 290.263,
        "y": 36.197,
        "z": 377.959,
        "energy_residual": 100.0,
        "energy_node": 100.0
    },
    {
        "id": 328,
        "x": 296.115,
        "y": 74.618,
        "z": 43.692,
        "energy_residual": 100.0,
        "energy_node": 100.0
    },
    {
        "id": 329,
        "x": 291.699,
        "y": 60.692,
        "z": 88.561,
        "energy_residual": 100.0,
        "energy_node": 100.0
    },
    {
        "id": 330,
        "x": 250.609,
        "y": 66.141,
        "z": 111.478,
        "energy_residual": 100.0,
        "energy_node": 100.0
    },
    {
        "id": 331,
        "x": 275.343,
        "y": 86.843,
        "z": 154.884,
        "energy_residual": 100.0,
        "energy_node": 100.0
    },
    {
        "id": 332,
        "x": 275.746,
        "y": 96.921,
        "z": 211.432,
        "energy_residual": 100.0,
        "energy_node": 100.0
    },
    {
        "id": 333,
        "x": 283.857,
        "y": 79.644,
        "z": 250.503,
        "energy_residual": 100.0,
        "energy_node": 100.0
    },
    {
        "id": 334,
        "x": 273.791,
        "y": 85.439,
        "z": 302.199,
        "energy_residual": 100.0,
        "energy_node": 100.0
    },
    {
        "id": 335,
        "x": 293.976,
        "y": 76.004,
        "z": 351.533,
        "energy_residual": 100.0,
        "energy_node": 100.0
    },
    {
        "id": 336,
        "x": 261.221,
        "y": 147.684,
        "z": 29.116,
        "energy_residual": 100.0,
        "energy_node": 100.0
    },
    {
        "id": 337,
        "x": 255.374,
        "y": 114.377,
        "z": 72.835,
        "energy_residual": 100.0,
        "energy_node": 100.0
    },
    {
        "id": 338,
        "x": 251.048,
        "y": 120.581,
        "z": 124.473,
        "energy_residual": 100.0,
        "energy_node": 100.0
    },
    {
        "id": 339,
        "x": 262.184,
        "y": 129.432,
        "z": 187.662,
        "energy_residual": 100.0,
        "energy_node": 100.0
    },
    {
        "id": 340,
        "x": 261.792,
        "y": 131.025,
        "z": 231.981,
        "energy_residual": 100.0,
        "energy_node": 100.0
    },
    {
        "id": 341,
        "x": 297.427,
        "y": 138.914,
        "z": 292.417,
        "energy_residual": 100.0,
        "energy_node": 100.0
    },
    {
        "id": 342,
        "x": 274.521,
        "y": 109.267,
        "z": 349.791,
        "energy_residual": 100.0,
        "energy_node": 100.0
    },
    {
        "id": 343,
        "x": 256.468,
        "y": 123.573,
        "z": 353.405,
        "energy_residual": 100.0,
        "energy_node": 100.0
    },
    {
        "id": 344,
        "x": 297.193,
        "y": 198.246,
        "z": 35.969,
        "energy_residual": 100.0,
        "energy_node": 100.0
    },
    {
        "id": 345,
        "x": 267.5,
        "y": 162.719,
        "z": 63.265,
        "energy_residual": 100.0,
        "energy_node": 100.0
    },
    {
        "id": 346,
        "x": 256.365,
        "y": 176.29,
        "z": 107.091,
        "energy_residual": 100.0,
        "energy_node": 100.0
    },
    {
        "id": 347,
        "x": 265.837,
        "y": 181.335,
        "z": 186.377,
        "energy_residual": 100.0,
        "energy_node": 100.0
    },
    {
        "id": 348,
        "x": 251.214,
        "y": 171.506,
        "z": 232.606,
        "energy_residual": 100.0,
        "energy_node": 100.0
    },
    {
        "id": 349,
        "x": 292.662,
        "y": 173.766,
        "z": 298.46,
        "energy_residual": 100.0,
        "energy_node": 100.0
    },
    {
        "id": 350,
        "x": 263.282,
        "y": 150.675,
        "z": 324.188,
        "energy_residual": 100.0,
        "energy_node": 100.0
    },
    {
        "id": 351,
        "x": 262.806,
        "y": 191.186,
        "z": 361.639,
        "energy_residual": 100.0,
        "energy_node": 100.0
    },
    {
        "id": 352,
        "x": 265.531,
        "y": 239.561,
        "z": 35.757,
        "energy_residual": 100.0,
        "energy_node": 100.0
    },
    {
        "id": 353,
        "x": 277.903,
        "y": 235.247,
        "z": 70.932,
        "energy_residual": 100.0,
        "energy_node": 100.0
    },
    {
        "id": 354,
        "x": 250.266,
        "y": 200.568,
        "z": 125.561,
        "energy_residual": 100.0,
        "energy_node": 100.0
    },
    {
        "id": 355,
        "x": 254.165,
        "y": 202.554,
        "z": 198.276,
        "energy_residual": 100.0,
        "energy_node": 100.0
    },
    {
        "id": 356,
        "x": 292.95,
        "y": 207.601,
        "z": 200.033,
        "energy_residual": 100.0,
        "energy_node": 100.0
    },
    {
        "id": 357,
        "x": 297.083,
        "y": 213.916,
        "z": 259.295,
        "energy_residual": 100.0,
        "energy_node": 100.0
    },
    {
        "id": 358,
        "x": 284.575,
        "y": 205.445,
        "z": 313.232,
        "energy_residual": 100.0,
        "energy_node": 100.0
    },
    {
        "id": 359,
        "x": 298.755,
        "y": 231.973,
        "z": 376.034,
        "energy_residual": 100.0,
        "energy_node": 100.0
    },
    {
        "id": 360,
        "x": 269.896,
        "y": 288.725,
        "z": 7.048,
        "energy_residual": 100.0,
        "energy_node": 100.0
    },
    {
        "id": 361,
        "x": 298.367,
        "y": 293.056,
        "z": 80.883,
        "energy_residual": 100.0,
        "energy_node": 100.0
    },
    {
        "id": 362,
        "x": 252.145,
        "y": 285.043,
        "z": 145.664,
        "energy_residual": 100.0,
        "energy_node": 100.0
    },
    {
        "id": 363,
        "x": 276.229,
        "y": 267.711,
        "z": 156.014,
        "energy_residual": 100.0,
        "energy_node": 100.0
    },
    {
        "id": 364,
        "x": 287.745,
        "y": 294.251,
        "z": 205.013,
        "energy_residual": 100.0,
        "energy_node": 100.0
    },
    {
        "id": 365,
        "x": 287.949,
        "y": 250.853,
        "z": 298.353,
        "energy_residual": 100.0,
        "energy_node": 100.0
    },
    {
        "id": 366,
        "x": 280.753,
        "y": 277.622,
        "z": 314.797,
        "energy_residual": 100.0,
        "energy_node": 100.0
    },
    {
        "id": 367,
        "x": 296.465,
        "y": 263.295,
        "z": 391.407,
        "energy_residual": 100.0,
        "energy_node": 100.0
    },
    {
        "id": 368,
        "x": 299.255,
        "y": 339.17,
        "z": 25.949,
        "energy_residual": 100.0,
        "energy_node": 100.0
    },
    {
        "id": 369,
        "x": 253.304,
        "y": 323.621,
        "z": 71.913,
        "energy_residual": 100.0,
        "energy_node": 100.0
    },
    {
        "id": 370,
        "x": 260.14,
        "y": 321.179,
        "z": 117.888,
        "energy_residual": 100.0,
        "energy_node": 100.0
    },
    {
        "id": 371,
        "x": 258.184,
        "y": 322.069,
        "z": 163.14,
        "energy_residual": 100.0,
        "energy_node": 100.0
    },
    {
        "id": 372,
        "x": 276.103,
        "y": 301.758,
        "z": 245.312,
        "energy_residual": 100.0,
        "energy_node": 100.0
    },
    {
        "id": 373,
        "x": 290.818,
        "y": 327.629,
        "z": 292.59,
        "energy_residual": 100.0,
        "energy_node": 100.0
    },
    {
        "id": 374,
        "x": 298.12,
        "y": 305.526,
        "z": 331.542,
        "energy_residual": 100.0,
        "energy_node": 100.0
    },
    {
        "id": 375,
        "x": 299.9,
        "y": 349.394,
        "z": 380.166,
        "energy_residual": 100.0,
        "energy_node": 100.0
    },
    {
        "id": 376,
        "x": 256.401,
        "y": 379.16,
        "z": 0.103,
        "energy_residual": 100.0,
        "energy_node": 100.0
    },
    {
        "id": 377,
        "x": 259.946,
        "y": 397.806,
        "z": 66.522,
        "energy_residual": 100.0,
        "energy_node": 100.0
    },
    {
        "id": 378,
        "x": 281.92,
        "y": 364.043,
        "z": 147.391,
        "energy_residual": 100.0,
        "energy_node": 100.0
    },
    {
        "id": 379,
        "x": 286.428,
        "y": 366.483,
        "z": 189.588,
        "energy_residual": 100.0,
        "energy_node": 100.0
    },
    {
        "id": 380,
        "x": 255.408,
        "y": 369.616,
        "z": 211.061,
        "energy_residual": 100.0,
        "energy_node": 100.0
    },
    {
        "id": 381,
        "x": 284.186,
        "y": 355.122,
        "z": 269.851,
        "energy_residual": 100.0,
        "energy_node": 100.0
    },
    {
        "id": 382,
        "x": 263.832,
        "y": 375.317,
        "z": 317.495,
        "energy_residual": 100.0,
        "energy_node": 100.0
    },
    {
        "id": 383,
        "x": 285.321,
        "y": 351.229,
        "z": 381.699,
        "energy_residual": 100.0,
        "energy_node": 100.0
    },
    {
        "id": 384,
        "x": 311.529,
        "y": 13.435,
        "z": 40.013,
        "energy_residual": 100.0,
        "energy_node": 100.0
    },
    {
        "id": 385,
        "x": 347.778,
        "y": 15.828,
        "z": 91.34,
        "energy_residual": 100.0,
        "energy_node": 100.0
    },
    {
        "id": 386,
        "x": 305.2,
        "y": 31.699,
        "z": 137.552,
        "energy_residual": 100.0,
        "energy_node": 100.0
    },
    {
        "id": 387,
        "x": 307.799,
        "y": 21.3,
        "z": 194.635,
        "energy_residual": 100.0,
        "energy_node": 100.0
    },
    {
        "id": 388,
        "x": 305.179,
        "y": 0.905,
        "z": 229.529,
        "energy_residual": 100.0,
        "energy_node": 100.0
    },
    {
        "id": 389,
        "x": 321.777,
        "y": 39.934,
        "z": 296.173,
        "energy_residual": 100.0,
        "energy_node": 100.0
    },
    {
        "id": 390,
        "x": 314.958,
        "y": 19.42,
        "z": 324.314,
        "energy_residual": 100.0,
        "energy_node": 100.0
    },
    {
        "id": 391,
        "x": 329.408,
        "y": 49.193,
        "z": 384.867,
        "energy_residual": 100.0,
        "energy_node": 100.0
    },
    {
        "id": 392,
        "x": 319.477,
        "y": 63.188,
        "z": 47.231,
        "energy_residual": 100.0,
        "energy_node": 100.0
    },
    {
        "id": 393,
        "x": 306.777,
        "y": 86.013,
        "z": 96.27,
        "energy_residual": 100.0,
        "energy_node": 100.0
    },
    {
        "id": 394,
        "x": 333.233,
        "y": 71.153,
        "z": 109.95,
        "energy_residual": 100.0,
        "energy_node": 100.0
    },
    {
        "id": 395,
        "x": 318.374,
        "y": 85.344,
        "z": 182.477,
        "energy_residual": 100.0,
        "energy_node": 100.0
    },
    {
        "id": 396,
        "x": 346.399,
        "y": 93.343,
        "z": 240.808,
        "energy_residual": 100.0,
        "energy_node": 100.0
    },
    {
        "id": 397,
        "x": 345.573,
        "y": 63.817,
        "z": 268.476,
        "energy_residual": 100.0,
        "energy_node": 100.0
    },
    {
        "id": 398,
        "x": 318.995,
        "y": 78.023,
        "z": 333.411,
        "energy_residual": 100.0,
        "energy_node": 100.0
    },
    {
        "id": 399,
        "x": 314.336,
        "y": 50.973,
        "z": 369.961,
        "energy_residual": 100.0,
        "energy_node": 100.0
    }
]